MANIFEST.in
setup.py
aivagent/__init__.py
aivagent/aivComfy.cp310-win_amd64.pyd
aivagent/aivComfy.cp311-win_amd64.pyd
aivagent/aivComfy.cp312-win_amd64.pyd
aivagent/aivComfy.cp39-win_amd64.pyd
aivagent/aivapp.py
aivagent/aivbot.py
aivagent/aivmedia.py
aivagent/aivmmap.cp310-win_amd64.pyd
aivagent/aivmmap.cp311-win_amd64.pyd
aivagent/aivmmap.cp312-win_amd64.pyd
aivagent/aivmmap.cp39-win_amd64.pyd
aivagent/aivtool.py
aivagent.egg-info/PKG-INFO
aivagent.egg-info/SOURCES.txt
aivagent.egg-info/dependency_links.txt
aivagent.egg-info/requires.txt
aivagent.egg-info/top_level.txt